data_demand_mapper/ __init__.py
data_demand_mapper/README.md
data_demand_mapper/toolkit.py
data_demand_mapper-0.2.5.dist-info/licenses/LICENSE
data_demand_mapper-0.2.5.dist-info/METADATA
data_demand_mapper-0.2.5.dist-info/WHEEL
data_demand_mapper-0.2.5.dist-info/top_level.txt
data_demand_mapper-0.2.5.dist-info/RECORD
