Metadata-Version: 2.4
Name: data_demand_mapper
Version: 0.2.5
Summary: A package for identifying and scoring third-party data buyers in U.S. federal job postings from USAJobs.
Author: Rory G. Quinlan
License: MIT
Project-URL: Homepage, https://github.com/RoryQo/Public-Sector-Data-Demand_Research-Framework-For-Market-Analysis-And-Classification
Requires-Python: >=3.8
License-File: LICENSE
Requires-Dist: pandas
Requires-Dist: numpy
Requires-Dist: scikit-learn
Requires-Dist: nltk
Requires-Dist: requests
Requires-Dist: rapidfuzz
Requires-Dist: joblib
Dynamic: license-file
